multidaq/__init__.py
multidaq/biovisionMultiDaq.dll
multidaq/hdf_stream.py
multidaq/libbiovisionMultiDaq.so
multidaq/multidaq.py
multidaq/tMsg.py
multidaq-1.2.0.dist-info/LICENSE
multidaq-1.2.0.dist-info/METADATA
multidaq-1.2.0.dist-info/WHEEL
multidaq-1.2.0.dist-info/top_level.txt
multidaq-1.2.0.dist-info/RECORD
