Metadata-Version: 2.1
Name: multidaq
Version: 1.2.0
Summary: Python interface to biovision digitizers. (64 bit Windows or Linux OS)
Author-email: Tantor GmbH <info@tantor.de>
License: MIT License
Project-URL: Homepage, https://github.com/biodaq/biovision/
Project-URL: Bug Reports, https://github.com/biodaq/biovision/issues
Project-URL: Source, https://github.com/biodaq/biovision/tree/main/share/python/multidaq/
Keywords: digitizer,biovision,biomechanics,driver
Classifier: Programming Language :: Python :: 3
Classifier: Operating System :: Microsoft :: Windows :: Windows 10
Classifier: Operating System :: POSIX :: Linux
Classifier: Topic :: Scientific/Engineering
Classifier: Topic :: System :: Hardware :: Hardware Drivers
Classifier: Development Status :: 4 - Beta
Classifier: Intended Audience :: Developers
Classifier: Intended Audience :: Science/Research
Requires-Python: >=3.8
License-File: LICENSE
Requires-Dist: numpy
Requires-Dist: h5py
